django_vises/__init__.py
django_vises/admin.py
django_vises/apps.py
django_vises/tests.py
django_vises/common/enum.py
django_vises/db/__init__.py
django_vises/db/influxdb2.py
django_vises/db/redis_set.py
django_vises/db/model/__init__.py
django_vises/db/model/base.py
django_vises/db/model/helpers.py
django_vises/deploy/__init__.py
django_vises/deploy/deploy_stage.py
django_vises/deploy/git.py
django_vises/deploy/sentry.py
django_vises/django_settings/__init__.py
django_vises/django_settings/context_processors.py
django_vises/django_settings/env_var.py
django_vises/django_settings/helpers.py
django_vises/logging/__init__.py
django_vises/logging/middleware.py
django_vises/task/__init__.py
django_vises/task/celery.py
django_vises/templatetags/__init__.py
django_vises/templatetags/vises.py
django_vises-1.7.0.dist-info/licenses/LICENSE
django_vises-1.7.0.dist-info/METADATA
django_vises-1.7.0.dist-info/WHEEL
django_vises-1.7.0.dist-info/top_level.txt
django_vises-1.7.0.dist-info/RECORD
