Metadata-Version: 2.4
Name: django-vises
Version: 1.7.0
Summary: Django Vises.
Author: Rex Zhang
Author-email: rex.zhang@gmail.com
Keywords: django
Classifier: Development Status :: 4 - Beta
Classifier: Framework :: Django
Requires-Python: >=3.13
License-File: LICENSE
Requires-Dist: django>=5.2
Requires-Dist: uuid-backport; python_version < "3.14"
Dynamic: license-file
